{"ts":"2026-04-25T10:03:31.998Z","source":"farmaciasguardia.farmaceuticos.com","territorio":"malaga","count":18,"schema":["lat","lng","direccion","poblacion","telefono","cp","horarioGuardia","horarioGuardiaDesc"],"guardias":[[37.20778,-4.65816,"Sanchez Lora Antonio · C/ Peñuelas Núm. 1","Alameda","952710006","29530","",""],[36.66275,-4.56275,"Hernandez Hernandez Maria T / Farrugia Melgar Isabel · Las Eras Local 3 (Urb. Cortijos Del Sol)","Alhaurin De La Torre","","29130","NOCHE",""],[37.01837,-4.55966,"Perea Orpez Jose Jorge · Plaza Del Portichuelo, 4","Antequera","952842148","29200","",""],[36.73646,-4.61271,"Arjona Pino Juan Jesus · C/ Marbella Num. 26","Cartama - Estacion","952420337","29580","",""],[37.26854,-4.41395,"Gallardo Medina Manuel · Juan Carlos I, 12","Cuevas De San Marcos.","952727004","29210","",""],[36.42681,-5.14685,"Carrillo Marti Borja Jose · Avda. Padre Cura Rotonda Hidralia","Estepona","952800576","29680","",""],[36.54416,-4.63153,"Cervera Rodriguez De Tembleque M Pilar - Fontecha Olid M Purificacion · Monda, 1","() - Fuengirola","952461788","","",""],[36.53884,-4.6234,"Gonzalez Benjumea Rocio · Av. Jesus Santos Rein N 21 (Esq. C/ Feria Jerez)","() - Fuengirola","952750977","","",""],[37.12587,-4.65789,"Martinez Maraver Andres · C/ La Union Num. 29","Mollina","952740173","29532","",""],[36.7292,-4.43449,"De La Linde Palomino, Encarnacion · Blas De Lezo, 25","Málaga","952305941","29011","NOCHE","Sector Arroyo De Los Angeles"],[36.71498,-4.44766,"Conejo Mostajo Ricardo - Lopez Perez Inmaculada · Av Andalucia, 61 (Carranque)","Málaga","951955087","29007","NOCHE","Sector Carranque"],[36.7213,-4.42164,"Mendoza Povedano Carlos · Imperio Argentina, 15 Ed Ferrovial 3 Lc3","Málaga","952211923","29006","NOCHE","Sector Carretera De Cadiz"],[36.7213,-4.42164,"Martinez Molina Sara Y Marina · Avda. Molier, 41 (Las Piramides)","Málaga","952244722","29004","NOCHE","Sector Carretera De Cadiz"],[36.7213,-4.42164,"Utrera Varela Rosa M / Ruiz Utrera Pablo · C/. La Hoz Num. 27 (Anterior A C/. Ayala) Junto Mercado De Huelin. Bda. De Huelin","Málaga","952310642","29002","NOCHE","Sector Carretera De Cadiz"],[36.7213,-4.42164,"Navarro Luna, Ana M · C/. Villanueva De Tapia, 14 Local 3 (Urb. Litoral Frente Hospital Quiron)","Málaga","952241987","29004","NOCHE","Sector Carretera De Cadiz"],[36.7213,-4.42164,"Castro Jaen Maria, Eugenia / Castro Jaen Guillermo · Navarro Ledesma, 241 Edif Las Adelfas","Málaga","952629383","29010","NOCHE","Sector Consul-Teatinos"],[36.7213,-4.42164,"Battikhi Vilar Boris · Paseo De Los Tilos Num. 30","Málaga","952311693","29006","NOCHE","Sector Los Tilos"],[36.7213,-4.42164,"Camacho Gonzalez, Inocencia · Paseo De Reding, 17 (Frente Plaza De Toros)","Málaga","952223731","29016","NOCHE","Sector Malagueta"]]}