{"ts":"2026-05-18T09:42:03.645Z","source":"farmaciasguardia.farmaceuticos.com","territorio":"malaga","count":24,"schema":["lat","lng","direccion","poblacion","telefono","cp","horarioGuardia","horarioGuardiaDesc"],"guardias":[[37.20778,-4.65816,"Sanchez Lora Antonio · C/ Peñuelas Núm. 1","Alameda","952710006","29530","",""],[36.6373,-4.69162,"Carrillo Delgado Esmeralda E. · Avda Blas Infante, 25","Alhaurin El Grande","","","",""],[37.26854,-4.41395,"Gallardo Medina Manuel · Juan Carlos I, 12","Cuevas De San Marcos.","952727004","29210","",""],[36.42681,-5.14685,"Carrillo Marti Borja Jose · Avda. Padre Cura Rotonda Hidralia","Estepona","952800576","29680","",""],[36.54416,-4.63153,"Cervera Rodriguez De Tembleque M Pilar - Fontecha Olid M Purificacion · Monda, 1","Fuengirola","952461788","","",""],[36.53884,-4.6234,"Gonzalez Benjumea Rocio · Av. Jesus Santos Rein N 21 (Esq. C/ Feria Jerez)","Fuengirola","952750977","","",""],[36.7292,-4.43449,"De La Linde Palomino, Encarnacion · Blas De Lezo, 25","Málaga","952305941","29011","NOCHE","Sector Arroyo De Los Angeles"],[36.715,-4.44767,"Conejo Mostajo Ricardo - Lopez Perez Inmaculada · Av Andalucia, 61 (Carranque)","Málaga","951955087","29007","NOCHE","Sector Carranque"],[36.76479,-4.4422,"Mendoza Povedano Carlos · Imperio Argentina, 15 Ed Ferrovial 3 Lc3","Málaga","952211923","29006","NOCHE","Sector Carretera De Cadiz"],[36.76479,-4.4422,"Martinez Molina Sara Y Marina · Avda. Molier, 41 (Las Piramides)","Málaga","952244722","29004","NOCHE","Sector Carretera De Cadiz"],[36.76479,-4.4422,"Utrera Ruiz Pablo · C/. La Hoz Num. 27 (Anterior A C/. Ayala) Junto Mercado De Huelin. Bda. De Huelin","Málaga","952310642","29002","NOCHE","Sector Carretera De Cadiz"],[36.76479,-4.4422,"Navarro Luna, Ana M · C/. Villanueva De Tapia, 14 Local 3 (Urb. Litoral Frente Hospital Quiron)","Málaga","952241987","29004","NOCHE","Sector Carretera De Cadiz"],[36.72323,-4.41828,"Martinez Aragon Maria · Plaza De La Merced, 9","Málaga","952227844","29012","NOCHE","Sector Centro"],[36.72135,-4.42216,"Utrera Jordan, Emilio A · Pza. De La Constitucion, 8","Málaga","952211692","29008","NOCHE","Sector Centro"],[36.73255,-4.41515,"Romero Garcia Maria Pilar · C/ Larios Num. 8","Sector Centro","952211915","","NOCHE",""],[36.76479,-4.4422,"Tudela Von Schmiterlow Javier · C/. Emilio Thuiller Num. 68","Málaga","952657016","29014","NOCHE","Sector Ciudad Jardin"],[36.76479,-4.4422,"Castro Jaen Maria, Eugenia / Castro Jaen Guillermo · Navarro Ledesma, 241 Edif Las Adelfas","Málaga","952629383","29010","NOCHE","Sector Consul-Teatinos"],[36.76479,-4.4422,"Battikhi Vilar Boris · Paseo De Los Tilos Num. 30","Málaga","952311693","29006","NOCHE","Sector Los Tilos"],[36.76479,-4.4422,"Camacho Gonzalez, Inocencia · Paseo De Reding, 17 (Frente Plaza De Toros)","Málaga","952223731","29016","NOCHE","Sector Malagueta"],[36.76479,-4.4422,"Alba Palomo Jose Enrique · Castilla, S/N Edif El Castillar (Frente Centro De Salud Portada Alta)","Málaga","952392444","29007","NOCHE","Sector Portada Alta"],[36.76479,-4.4422,"Garrido Garfia Carlota · Av. Antonio Soler Núm. 19 (Rotonda)","Málaga","646582104","29010","NOCHE","Sector Soliva"],[36.76479,-4.4422,"Rubio Ruiz, Emilio · C/ Orson Welles Num. 8","Málaga","952210765","29010","NOCHE","Sector Teatinos - Parque Del Cine"],[36.76479,-4.4422,"Morales Burgos Jose Luis · C/. Orson Welles Num. 32","Málaga","951268684","29010","NOCHE","Sector Teatinos - Parque Del Cine"],[36.377,-5.24898,"Martinez Martinez Maria Angeles · Av. De La Paz Num. 3 (Sabinillas)","Manilva","952891361","29692","",""]]}