{"ts":"2026-05-04T08:29:15.806Z","source":"cofalicante.com","territorio":"alicante","count":22,"schema":["lat","lng","direccion","poblacion","telefono","cp","horarioGuardia","horarioGuardiaDesc"],"guardias":[[38.53993,-0.12028,"Lopez-Gasco Garcia, Carmen · Avda. EUROPA, Nº12","Benidorm","","03503","9:30-9:30",""],[38.08607,-0.72689,"Andres Cervera, Cristina · C/ Cortes Valencianas, Nº38","Rojales","","03170","20:00-9:00",""],[38.12167,-0.87899,"Manresa Gilabert, Maria Enrique · C/ Abajo, Nº13","Callosa De Segura","","03360","9:00-9:00",""],[38.23669,-0.81778,"Sorribes Vidal, Miguel Angel · C/ Santisima Trinidad, Nº90","Crevillent","","03330","9:00-9:00",""],[38.26526,-0.70236,"Avila Lanzas, Juan Jose · Avda. REINA VICTORIA, Nº30","Elche/Elx","","03201","9:00-9:00",""],[38.26213,-0.70786,"Gimenez Mateos, Esperanza Blanca · C/ Antonio Machado, Nº43","Elche/Elx","","03204","9:00-9:00",""],[38.26208,-0.66649,"Serna Zaplana, Manuel · C/ Salvador, Nº25","Elche/Elx","","03203","9:00-20:00",""],[38.2643,-0.70366,"Farmacia Devesa, C.B. · C/ Poeta Miguel Hernandez, Nº72","Elche/Elx","","03201","9:00-20:00",""],[38.47273,-0.78875,"Garcia De Reparaz Y Yelo, Fernando · Avda. DE LAS ACACIAS, Nº29","Elda","","03600","9:00-9:00",""],[38.08834,-0.65421,"Farmacia Mora · Avda. PAIS VALENCIANO, Nº29","Guardamar Del Segura","","03140","9:00-9:00",""],[38.54154,-0.50625,"De Prado Mas, Francisco · Avda. CONSTITUCION, Nº10","Jijona/Xixona","965612187","03100","9:30-9:30",""],[38.78749,0.16108,"Farmacia Belchi, C.B. · Ronda De Colon, Nº4","Jávea/Xàbia","","03730","9:00-9:00",""],[38.40359,-1.04107,"Mauricio Heredia , Laura · Plaza DE ESPAÑA, Nº10","Pinoso","","03650","9:00-9:00",""],[38.38533,-0.75992,"Estebanez Consuegra, Juan Francisco · C/ Cervantes, Nº45","Novelda","","03660","9:30-9:30",""],[38.43552,-0.8439,"Badenes Catala, Rosario · C/ Luis Vidal, Nº12","Monóvar/Monòver","","03640","9:30-9:30",""],[38.38283,-0.73043,"Ayela Pastor, Maria Rosario · C/ Hermanos Kennedy, Nº3","Monforte Del Cid","","03670","13:30-17:00",""],[38.48352,-0.78711,"Cuenca Martinez, Juan Francisco · Avda. DE MADRID, Nº39","Petrer","","03610","9:00-9:00",""],[37.8646,-0.79116,"Farmacia Rafael Espuch C.B. · C/ Mayor, Nº21","Pilar De La Horadada","","03190","9:00-9:00",""],[38.53473,-0.82341,"Escolano Perez, Veronica · C/ Alicante, 28","Sax","","03630","9:00-9:00",""],[38.19366,-0.55681,"Torregrosa Macia, Jose Vicente · C/ De Elche, Nº36","Santa Pola","","03130","17:00-9:00",""],[38.19664,-0.55764,"Mares Calatayud, Maria · C/ Madrid, Nº10","Santa Pola","","03130","9:00-17:00",""],[38.64496,-0.86991,"Polo Marco, Sergio Antonio · Avda. CONSTITUCION, Nº98","Villena","","03400","9:00-9:00",""]]}