{"ts":"2026-04-27T08:00:13.956Z","source":"cofrm.com","territorio":"murcia","count":47,"schema":["lat","lng","direccion","poblacion","telefono","cp","horarioGuardia","horarioGuardiaDesc"],"guardias":[[37.74842,-0.94812,"MARIN SAURA, MARIA DOLORES · CL.FELICITO MANZANARES,5","TORRE PACHECO","968585872","30700","09:30-23:59","41 - TORRE PACHECO/ESTE"],[38.02044,-1.23633,"SATURNO DE LA VILLA, JAVIER Y AGUDO BARRIUSO, MARTA · AVENIDA LOS PULPITES, Nº 36","TORRES DE COTILLAS,LAS","968387218","30565","09:30-23:59","67 - LAS TORRES DE COTILLAS"],[37.96927,-1.21563,"DELGADO ALCAZAR, CONCEPCION · AVENIDA MARTINEZ CAMPOS, Nº 1","ALCANTARILLA","968800368","30820","09:30-23:59","2 - ALCANTARILLA/SANGONERA LA SECA"],[37.73739,-0.85815,"PARADA MARTINEZ, MARIA ANTONIA · CL.SAN VALENTIN, Nº 19, ESQUINA CL.CAPITAN CORTES","ALCAZARES,LOS","968170545","30710","09:30-23:59","73 - LOS ALCAZARES"],[37.62021,-0.87532,"BARCELO VAZQUEZ, MARIA · CALLE EMBUDO, Nº 2, ESQUINA CALLE REAL","UNION,LA","968560737","30360","09:30-23:59","42 - LA UNION"],[37.56953,-1.26329,"GARCIA MORENO, MERCEDES · AVENIDA DOCTOR MECA, ESQUINA CON CALLE PEATONAL","PUERTO DE MAZARRON","968153781","30860","09:30-23:59","82 - PUERTO DE MAZARRON"],[37.62165,-1.00508,"DESMONTS SALAZAR, JUAN · AVENIDA NUEVA CARTAGENA, Nº 3","CARTAGENA","968316242","30310","00:00-23:59","28 - CARTAGENA/SAN ANTON"],[37.77487,-1.49398,"LADRON DE GUEVARA RUIZ, CARMEN · CL.SANTOMERA, Nº 17","TOTANA","968421811","30850","09:30-23:59","50 - TOTANA/NORTE"],[38.05335,-1.21187,"GOMEZ GARCIA, ANA MARIA · C/MAYOR,18","MOLINA DE SEGURA","968610183","30500","09:30-23:59","66 - MOLINA/SUR"],[37.72336,-1.17218,"PEREZ-GUILLERMO VALDES, MARIA DEL CARMEN · C/LEDESMA RAMOS,2","FUENTE ALAMO","968597181","30320","00:00-23:59","37 - FUENTE ALAMO"],[38.09205,-1.7982,"CUADRADO GARCIA, ISABEL · JUAN ANTONIO LOPEZ SANCHEZ, S/N","ALMUDEMA,LA","968704204","30410","00:00-23:59","54 - CARAVACA/BARRANDA"],[38.61593,-1.11993,"LUCAS TOMAS, JOSE MARIANO · CALLE SAN LUIS, Nº 32","YECLA","968791203","30510","09:30-23:59","76 - YECLA/OESTE"],[38.1798,-1.36771,"ROJAS GARCIA, FRANCISCO · CTRA.DE LA ESTACION,16","BLANCA","968778301","30540","00:00-23:59","70 - BLANCA"],[37.6158,-1.02116,"RODRIGUEZ LUACES, MARIA FATIMA · CALLE GUAYAQUIL, Nº 14, ESQUINA CALLE VIÑA DEL MAR, URBANIZACIÓN LA VAGUADA","CARTAGENA","968163475","30393","09:30-23:59","27 - CARTAGENA/MOLINOS MARFAGONES"],[37.80582,-0.7999,"SERNA OÑATE, ANA Y SERNA OÑATE, ALVARO · CALLE CANOVAS DEL CASTILLO, Nº 101, ESQUINA CALLE GASCÓN","SANTIAGO DE LA RIBERA","968179289","30720","00:00-23:59","39 - SAN JAVIER"],[37.97546,-1.07285,"ZARAGOZA NOGUERA, ROGELIO · MAYOR,17","BENIAJAN","968821679","30570","09:30-23:59","13 - MURCIA/BENIAJAN"],[38.24287,-1.42188,"LUCAS ELIO, MARIA CRUZ Y MONICA · CL.GRAN VIA, Nº 7","CIEZA","968761226","30530","09:30-23:59","63 - CIEZA/ESTE"],[37.55945,-1.81045,"GARCIA GARCIA, FERNANDO JOSE · CALLE SAN FRANCISCO, Nº 25","PUERTO LUMBRERAS","968402031","30890","09:30-23:59","49 - PUERTO LUMBRERAS"],[38.18882,-1.89183,"MARTINEZ SANCHEZ,ELENA · CONSTITUCION,8","MORATALLA","968730253","30440","09:30-23:59","56 - MORATALLA"],[38.03626,-1.49195,"PEIRO BERENGUER, RAFAEL, Y PRADERA BLANCO, MARIA EMILIA · CL.PINTOR VILLACIS, S/N","MULA","968660533","30170","09:30-23:59","5 - MULA"],[38.22912,-1.70604,"ROSIQUE TABUENCA, ARANZAZU · CL.BARRIONUEVO POZO, Nº 30, ESQUINA CALLE ESPARTEROS","CALASPARRA","968720356","30420","00:00-23:59","52 - CALASPARRA"],[38.04708,-1.66753,"FIGUEROA SORIANO, SALVADOR, HEREDEROS Y FIGUEROA MORALES, MERCEDES · CL.FRANCISCO PUERTA, ESQUINA A CALDERON DE LA BARCA","BULLAS","968652080","30180","09:30-23:59","51 - BULLAS"],[38.04546,-1.00235,"GARRIDO SAEZ, ANA MARIA · CL. CALVO SOTELO, Nº 5","BENIEL","968600240","30130","09:30-23:59","4 - BENIEL"],[38.20782,-1.04232,"OLIVER HURTADO, MARIA · CORAZON DE JESUS, 8","ABANILLA","968680619","30640","09:30-23:59","59 - ABANILLA"],[37.85017,-1.4254,"SERRANO LANDABEREA, ELENA MARIA · CL. JUAN CARLOS I,50","ALHAMA DE MURCIA","968630047","30840","00:00-23:59","3 - ALHAMA"],[38.09201,-1.79476,"CASTILLO GUERRERO,JOSE LUIS · CL.CAMINO VERDE, Nº 1","CEHEGIN","968740519","30430","09:30-23:59","55 - CEHEGIN"],[38.17864,-1.12547,"SANCHEZ POLO, ALBERTO · AVENIDA SALVADOR ALLENDE, Nº 18","FORTUNA","968685048","30620","09:30-23:59","64 - FORTUNA"],[37.88652,-1.3529,"PEREZ NAVARRO, RUBEN · MAESTRO ESPADA,S/N","LIBRILLA","968658636","30892","09:30-23:59","90 - LIBRILLA"],[38.20748,-1.39451,"GOMEZ ABELLAN, JESUS JOAQUIN · AVDA. CIEZA, 40","ABARAN","968770478","30550","00:00-23:59","60 - ABARAN"],[37.72905,-1.08371,"ROS SANCHEZ, ANTONIA · CALLE ONESIMO REDONDO, Nº 2","LOBOSILLO","968878066","30331","09:30-23:59","24 - MURCIA/CAMPO DE CARTAGENA"],[37.60647,-0.98155,"CANO PEREZ, MIGUEL · CALLE JUAN DE LA COSA, Nº 7","CARTAGENA","968506883","30203","00:00-23:59","34 - CARTAGENA/CASCO ANTIGUO"],[38.10476,-1.86332,"GUERRERO QUADRADO,PEDRO · CALLE CORREDERA, Nº 16","CARAVACA DE LA CRUZ","968702389","30400","09:30-23:59","53 - CARAVACA"],[37.80551,-0.8398,"MILLA SANCHEZ, ANTONIO · CALLE ALICANTE, Nº 1, ESQUINA CARRETERA DE BALSICAS","SAN JAVIER","968571491","30730","00:00-23:59","39 - SAN JAVIER"],[38.08397,-1.25342,"FERNANDEZ SORIA, JULIA · CL.PORTICHUELO, Nº 14 Y 16","LORQUI","968690329","30564","09:30-23:59","72 - LORQUI"],[37.94151,-1.16766,"NAVARRO MARTINEZ, FRANCISCO LUIS Y NAVARRO PEREZ-ONTIVEROS, MARIA · CALLE LORCA, S/N, CIUDAD JARDIN LA PAZ","PALMAR,EL","968882236","30120","00:00-23:59","23 - MURCIA/EL PALMAR"],[37.41244,-1.58629,"GARCIA GARCIA, JUANA INES · CL. J.JIMENEZ RUANO, S/N","AGUILAS","968413510","30880","09:30-23:59","68 - AGUILAS/NORTE"],[38.11506,-1.30765,"MARTINEZ CARRILLO,Ma.DELIA · AVENIDA ANTONETE GALVEZ, Nº 38, ESQUINA CALLE ALHELI","ARCHENA","968671857","30600","00:00-23:59","62 - ARCHENA"],[38.07951,-1.27182,"JARA PEREZ, EZEQUIEL RAMON Y JARA CASCALES, ISABEL · PLAZA NUEVA, Nº 6","CEUTÍ","968690188","30562","09:30-23:59","71 - CEUTI"],[37.81535,-0.7882,"MUNUERA GONZALEZ, JUANA Y MARTINEZ MONTEAGUDO, ENRIQUE JOSE · CALLE GARCIA MORATO, ESQUINA A GENERAL CASS0LA","LO PAGAN","968180893","30740","09:30-23:59","40 - SAN PEDRO DEL PINATAR"],[37.8449,-1.87703,"RODRIGUEZ MORENO, JOSEFA ELOISA · CALLE SASTRA, Nº 2, ESQUINA CALLE LARGA-ZARCILLA DE RAMOS","ZARCILLA DE RAMOS- LORCA","968499738","30810","00:00-23:59","48 - LORCA/LA PACA"],[38.06143,-1.04669,"LLAMAS LAZARO, FERNANDO · CALLE DE LOS PASOS, Nº 12-D","SANTOMERA","968865192","30140","09:30-23:59","25 - SANTOMERA"],[37.60962,-0.99286,"CRESPO GALVEZ, MARIA DOLORES · ALAMEDA DE SAN ANTON, 16","CARTAGENA","968501936","30205","00:00-23:59","26 - CARTAGENA/OESTE"],[37.64833,-0.86502,"CONESA MARTINEZ, ANA MARIA Y CALATRAVA TORRES, MANUEL · CL.CASTELAR, Nº 25","ALGAR,EL","968135921","30366","09:30-23:59","36 - CARTAGENA/MAR MENOR"],[38.14067,-1.32996,"CAYUELAS NAVARRO, MIRIAN · CALLE HEREDIA ESPINOLA, Nº 11","ULEA","968698310","30612","09:30-23:59","62 - ARCHENA"],[37.6739,-0.73065,"MARTINEZ SABATER, HELENA · AVENIDA GRAN VIA DE LA MANGA, KM. 4.7, EDF. COMERCIAL 'EL FLAMENCO', COMPLEJO URBANISTICO 'ZOCO' (JUNTO A LA GASO","LA MANGA DEL MAR MENOR","968143635","30380","09:30-23:59","43 - LA MANGA"],[38.04986,-1.24206,"RIQUELME GARCIA, CONSUELO · CALLE MAYOR, Nº 17","ALGUAZAS","868919991","30560","09:30-23:59","61 - ALGUAZAS"],[38.4807,-1.32239,"CHAMORRO GOMEZ, MIGUEL · CALLE IRENE LOPEZ HEREDIA, Nº 18","JUMILLA","968921992","30520","09:30-23:59","57 - JUMILLA"]]}